pyngleton/__init__.py
pyngleton-0.0.6.dist-info/METADATA
pyngleton-0.0.6.dist-info/WHEEL
pyngleton-0.0.6.dist-info/licenses/LICENSE
pyngleton-0.0.6.dist-info/RECORD
